bafficommons/__init__.py
bafficommons/cobani/__init__.py
bafficommons/cobani/rest/__init__.py
bafficommons/cobani/rest/models.py
bafficommons/runner/__init__.py
bafficommons/runner/baffialgorithms/__init__.py
bafficommons/runner/baffialgorithms/algorithms.py
bafficommons/runner/baffialgorithms/winnowing/__init__.py
bafficommons/runner/baffialgorithms/winnowing/impl/__init__.py
bafficommons/runner/baffialgorithms/winnowing/impl/config.py
bafficommons/runner/baffialgorithms/winnowing/impl/winnowing.py
bafficommons/runner/baffialgorithms/winnowing/impl/indexers/__init__.py
bafficommons/runner/baffialgorithms/winnowing/impl/indexers/winnowing_indexer.py
bafficommons/runner/baffialgorithms/winnowing/impl/preprocessors/__init__.py
bafficommons/runner/baffialgorithms/winnowing/impl/preprocessors/preprocesser.py
bafficommons/runner/baffialgorithms/winnowing/impl/searchers/__init__.py
bafficommons/runner/baffialgorithms/winnowing/impl/searchers/exact_searcher.py
bafficommons/runner/rest/__init__.py
bafficommons/runner/rest/models.py
bafficommons/storage/__init__.py
bafficommons/storage/rest/__init__.py
bafficommons/storage/rest/models.py
bafficommons-0.0.18.dist-info/LICENSE
bafficommons-0.0.18.dist-info/METADATA
bafficommons-0.0.18.dist-info/WHEEL
bafficommons-0.0.18.dist-info/top_level.txt
bafficommons-0.0.18.dist-info/RECORD
